dialogos/__init__.py
dialogos/admin.py
dialogos/authorization.py
dialogos/forms.py
dialogos/models.py
dialogos/signals.py
dialogos/tests.py
dialogos/urls.py
dialogos/views.py
dialogos/migrations/0001_initial.py
dialogos/migrations/__init__.py
dialogos/templatetags/__init__.py
dialogos/templatetags/dialogos_tags.py
geonode_dialogos-3.0.1.dist-info/LICENSE
geonode_dialogos-3.0.1.dist-info/METADATA
geonode_dialogos-3.0.1.dist-info/WHEEL
geonode_dialogos-3.0.1.dist-info/top_level.txt
geonode_dialogos-3.0.1.dist-info/RECORD
