Metadata-Version: 2.1
Name: geonode-dialogos
Version: 3.0.1
Summary: a flaggable comments app
Home-page: https://github.com/GeoNode/geonode-dialogos
Author: Eldarion
Author-email: development@eldarion.com
Maintainer-email: geonode-devel@lists.osgeo.org
License: BSD
Platform: UNKNOWN
Classifier: Development Status :: 3 - Alpha
Classifier: Environment :: Web Environment
Classifier: Intended Audience :: Developers
Classifier: License :: OSI Approved :: BSD License
Classifier: Operating System :: OS Independent
Classifier: Programming Language :: Python :: 3
Classifier: Framework :: Django
